<?xml version="1.0" encoding="utf-8" ?><dwsync><file name="fullcalendar.css" server="201.161.66.233//var/www/html/sigma/" local="3600204082" remote="320909690693206195" Dst="-1" /><file name="fullcalendar.js" server="201.161.66.233//var/www/html/sigma/" local="3600204082" remote="320909690693206212" Dst="-1" /><file name="fullcalendar.min.css" server="201.161.66.233//var/www/html/sigma/" local="3600204082" remote="320909690693206213" Dst="-1" /><file name="fullcalendar.min.js" server="201.161.66.233//var/www/html/sigma/" local="3600204082" remote="320909690693206219" Dst="-1" /><file name="fullcalendar.print.css" server="201.161.66.233//var/www/html/sigma/" local="3600204084" remote="320909690693206219" Dst="-1" /><file name="fullcalendar.print.min.css" server="201.161.66.233//var/www/html/sigma/" local="3600204084" remote="320909690693206220" Dst="-1" /><file name="gcal.js" server="201.161.66.233//var/www/html/sigma/" local="3600204082" remote="320909690693206220" Dst="-1" /><file name="gcal.min.js" server="201.161.66.233//var/www/html/sigma/" local="3600204082" remote="320909690693206220" Dst="-1" /><file name="locale-all.js" server="201.161.66.233//var/www/html/sigma/" local="3600204082" remote="320909690693206258" Dst="-1" /></dwsync>